{
  "db_name": "PostgreSQL",
  "query": "\n            select users.activity_status as \"status: ActivityStatus\", users.profile_picture_url, user_friends.note from user_friends\n            join users on users.id = user_friends.friend_id\n            where user_id = $1\n        ",
  "describe": {
    "columns": [
      {
        "ordinal": 0,
        "name": "status: ActivityStatus",
        "type_info": {
          "Custom": {
            "name": "status",
            "kind": {
              "Enum": [
                "online",
                "offline",
                "idle"
              ]
            }
          }
        }
      },
      {
        "ordinal": 1,
        "name": "profile_picture_url",
        "type_info": "Text"
      },
      {
        "ordinal": 2,
        "name": "note",
        "type_info": "Text"
      }
    ],
    "parameters": {
      "Left": [
        "Uuid"
      ]
    },
    "nullable": [
      false,
      false,
      false
    ]
  },
  "hash": "6d2fd4b67644ff103d0b6348bc56fd00b7731d72cc6e0eb0d2bc5c329a363883"
}
